prompt_cicd-0.2.2.dist-info/licenses/LICENSE
promptops/__init__.py
promptops/approval.py
promptops/cli.py
promptops/diff.py
promptops/env.py
promptops/exceptions.py
promptops/guard.py
promptops/loader.py
promptops/policies.py
promptops/prompt.py
promptops/renderer.py
promptops/utils.py
promptops/cache/__init__.py
promptops/cache/manager.py
promptops/cli/__init__.py
promptops/cli/console.py
promptops/cli/main.py
promptops/cost/__init__.py
promptops/cost/budget.py
promptops/lint/__init__.py
promptops/lint/linter.py
promptops/lint/rules.py
promptops/providers/__init__.py
promptops/providers/openai_provider.py
promptops/rollback/__init__.py
promptops/rollback/engine.py
promptops/rollback/store.py
promptops/safety/__init__.py
promptops/safety/scanner.py
promptops/scaffold/__init__.py
promptops/scaffold/generator.py
promptops/testing/__init__.py
promptops/testing/assertions.py
promptops/testing/llm_judge.py
promptops/testing/results.py
promptops/testing/runner.py
prompt_cicd-0.2.2.dist-info/METADATA
prompt_cicd-0.2.2.dist-info/WHEEL
prompt_cicd-0.2.2.dist-info/entry_points.txt
prompt_cicd-0.2.2.dist-info/top_level.txt
prompt_cicd-0.2.2.dist-info/RECORD
