Metadata-Version: 2.4
Name: prompt-cicd
Version: 0.2.2
Summary: CI/CD for AI Prompts - Test, lint, version, and deploy prompts with confidence
Author-email: Prabhnoor Singh <legendmoto@users.noreply.github.com>
License-Expression: MIT
Project-URL: Homepage, https://github.com/prabhnoor12/promptops
Project-URL: Documentation, https://github.com/prabhnoor12/promptops#readme
Project-URL: Repository, https://github.com/prabhnoor12/promptops
Project-URL: Changelog, https://github.com/prabhnoor12/promptops/blob/main/CHANGELOG.md
Project-URL: Issues, https://github.com/prabhnoor12/promptops/issues
Keywords: prompt-engineering,llm,ai,ci-cd,testing,linting,openai,anthropic,gpt,chatgpt
Classifier: Development Status :: 4 - Beta
Classifier: Environment :: Console
Classifier: Intended Audience :: Developers
Classifier: Operating System :: OS Independent
Classifier: Programming Language :: Python :: 3
Classifier: Programming Language :: Python :: 3.9
Classifier: Programming Language :: Python :: 3.10
Classifier: Programming Language :: Python :: 3.11
Classifier: Programming Language :: Python :: 3.12
Classifier: Topic :: Software Development :: Quality Assurance
Classifier: Topic :: Software Development :: Testing
Classifier: Topic :: Scientific/Engineering :: Artificial Intelligence
Classifier: Typing :: Typed
Requires-Python: >=3.9
License-File: LICENSE
Requires-Dist: click>=8.0
Requires-Dist: pyyaml>=6.0
Requires-Dist: openai>=1.0
Requires-Dist: rich>=13.0
Requires-Dist: jinja2>=3.0
Provides-Extra: dev
Requires-Dist: pytest>=7.0; extra == "dev"
Requires-Dist: pytest-cov>=4.0; extra == "dev"
Requires-Dist: pytest-asyncio>=0.21; extra == "dev"
Requires-Dist: mypy>=1.0; extra == "dev"
Requires-Dist: ruff>=0.1; extra == "dev"
Requires-Dist: black>=23.0; extra == "dev"
Requires-Dist: pre-commit>=3.0; extra == "dev"
Provides-Extra: anthropic
Requires-Dist: anthropic>=0.18; extra == "anthropic"
Provides-Extra: all
Requires-Dist: promptops[anthropic,dev]; extra == "all"
Dynamic: license-file
